mutable_primitives/__init__.py
mutable_primitives/base.py
mutable_primitives/bool.py
mutable_primitives/float.py
mutable_primitives/int.py
mutable_primitives/str.py
mutable_primitives-0.0.7.dist-info/LICENSE
mutable_primitives-0.0.7.dist-info/METADATA
mutable_primitives-0.0.7.dist-info/WHEEL
mutable_primitives-0.0.7.dist-info/top_level.txt
mutable_primitives-0.0.7.dist-info/RECORD
