Metadata-Version: 2.1
Name: mutable-primitives
Version: 0.0.7
Summary: Mutable classes of python primitives
Home-page: https://github.com/das-intensity/mutable-primitives
Author: Dr. Nick
Author-email: das-intensity@users.noreply.github.com
License: MIT Licence
Classifier: Programming Language :: Python :: 2
Classifier: Programming Language :: Python :: 2.7
Classifier: Programming Language :: Python :: 3
Classifier: Programming Language :: Python :: 3.4
Classifier: Programming Language :: Python :: 3.5
Classifier: Programming Language :: Python :: 3.6
Classifier: Programming Language :: Python :: 3.7
Classifier: Programming Language :: Python :: 3.8
Classifier: Programming Language :: Python :: 3.9
Classifier: Programming Language :: Python :: 3.10
License-File: LICENSE
